{"hash":"bab14123ba2aa6ecb3a11b17cb08d92dc823b388","data":{"post":{"id":"26ab8148581e562481ecbbdf74ff909b","title":"If we can design doors that make us feel stupid, then can’t we design the world to feel awesome?","content":"<p>BTW, <strong>everything</strong> is design.</p>\n<ul>\n<li>Chemists design molecules.</li>\n<li>Stylists design outfits.</li>\n<li>Coders design software systems.</li>\n<li>Transportation engineers design traffic flow.</li>\n<li>etc.</li>\n</ul>\n<p>So designing everything to feel awesome? Yeah, there’s a lot to learn.</p>\n<p><img src=\"https://cdn-images-1.medium.com/max/800/1*k3x4eNfGaG54H9skwyKeSA.png\"></p>\n","date":"September 21, 2018","timeToRead":1,"description":"I’m busy learning as much as I can about the world so that I can make that a reality — everything, awesome. Let’s start designing with a…","cover":null}},"context":{}}